LICENSE
README.md
setup.py
zxcglf/__init__.py
zxcglf/csv.py
zxcglf/debug.py
zxcglf/file.py
zxcglf/img.py
zxcglf/keyboard.py
zxcglf/mouse.py
zxcglf/password.py
zxcglf/path.py
zxcglf/system.py
zxcglf/time.py
zxcglf/tool.py
zxcglf/window.py
zxcglf/xlsx.py
zxcglf.egg-info/PKG-INFO
zxcglf.egg-info/SOURCES.txt
zxcglf.egg-info/dependency_links.txt
zxcglf.egg-info/requires.txt
zxcglf.egg-info/top_level.txt