Metadata-Version: 2.1
Name: zxcglf
Version: 1.0
Summary: 常用工具集合
Home-page: https://github.com/uiharukazari0105/zxcglf
Author: 初春飾利
Author-email: glf20041128@163.com
License: MIT
Platform: UNKNOWN
Classifier: Programming Language :: Python :: 3
Classifier: License :: OSI Approved :: MIT License
Classifier: Operating System :: OS Independent
Requires-Python: >=3
License-File: LICENSE
